{"cameraMode":{"drawMode":0,"name":"Shaded","section":"Shading Mode"},"sceneLighting":true,"audioPlay":false,"sceneViewState":{"showFog":true,"showMaterialUpdate":false,"showSkybox":true,"showFlares":true,"showImageEffects":true,"showParticleSystems":true},"in2DMode":false,"pivot":{"x":2.0919361114501955,"y":3.5540823936462404,"z":-13.639668464660645},"rotation":{"x":-0.21511231362819673,"y":-0.5409262776374817,"z":0.14519256353378297,"w":-0.8001810908317566},"size":12.455251693725586,"orthographic":false}